Metadata-Version: 2.1
Name: mamanteo-distributions
Version: 0.1
Summary: Binomial and Gaussian Distributions
Home-page: UNKNOWN
License: UNKNOWN
Platform: UNKNOWN
